{
    "BG": {
        "41.png": "3664479",
        "25.png": "1386321",
        "26.png": "3065851",
        "16.png": "4845174",
        "33.png": "2399573",
        "51.png": "4860219",
        "05.png": "510422",
        "37.png": "949093",
        "10.png": "435281",
        "46.png": "3982039",
        "11.png": "1254411",
        "08.png": "3107025",
        "35.png": "792049",
        "24.png": "3322601",
        "12.png": "592435",
        "40.png": "3240363",
        "06.png": "3262381",
        "47.png": "4316984",
        "01.png": "1849191",
        "56.png": "2517116",
        "04.png": "639730",
        "43.png": "1815356",
        "34.png": "194423",
        "02.png": "1664967",
        "27.png": "4136590",
        "53.png": "6395364",
        "42.png": "577190",
        "09.png": "399845",
        "07.png": "4007563",
        "19.png": "2789299",
        "48.png": "4083650",
        "38.png": "98120",
        "49.png": "3765965",
        "13.png": "843594",
        "29.png": "2166076",
        "28.png": "5007968",
        "23.png": "1275127",
        "36.png": "3940465",
        "57.png": "1922764",
        "22.png": "4704673",
        "55.png": "5882401",
        "17.png": "4583491",
        "20.png": "4170988",
        "59.png": "3093435",
        "15.png": "2892482",
        "54.png": "3612217",
        "21.png": "3038921",
        "39.png": "64089",
        "30.png": "4483827",
        "45.png": "896248",
        "31.png": "3187249",
        "03.png": "798969",
        "58.png": "1267185",
        "18.png": "4910132",
        "50.png": "5855739",
        "52.png": "5957559",
        "44.png": "700756",
        "32.png": "2961310",
        "14.png": "4713376"
    },
    "Ccp": {
        "41.png": "745467",
        "25.png": "820724",
        "26.png": "98043",
        "16.png": "129030",
        "33.png": "5923",
        "51.png": "2797",
        "05.png": "0",
        "37.png": "21704",
        "10.png": "11479",
        "46.png": "12899",
        "11.png": "44543",
        "08.png": "429787",
        "35.png": "0",
        "24.png": "193046",
        "12.png": "5474",
        "40.png": "140046",
        "06.png": "146016",
        "47.png": "83571",
        "01.png": "166821",
        "56.png": "0",
        "04.png": "352852",
        "43.png": "102350",
        "34.png": "48084",
        "02.png": "6969",
        "27.png": "368323",
        "53.png": "7518",
        "42.png": "58251",
        "09.png": "6030",
        "07.png": "562151",
        "19.png": "72598",
        "48.png": "17326",
        "38.png": "15626",
        "49.png": "0",
        "13.png": "31020",
        "29.png": "206667",
        "28.png": "1140495",
        "23.png": "101973",
        "36.png": "0",
        "57.png": "1527",
        "22.png": "20431",
        "55.png": "3494",
        "17.png": "62160",
        "20.png": "73235",
        "59.png": "0",
        "15.png": "489436",
        "54.png": "835708",
        "21.png": "12901",
        "39.png": "0",
        "30.png": "2121",
        "45.png": "428061",
        "31.png": "1181",
        "03.png": "22272",
        "58.png": "0",
        "18.png": "97574",
        "50.png": "12606",
        "52.png": "0",
        "44.png": "83817",
        "32.png": "0",
        "14.png": "837013"
    },
    "Gl": {
        "41.png": "6050",
        "25.png": "74484",
        "26.png": "107231",
        "16.png": "241522",
        "33.png": "158412",
        "51.png": "0",
        "05.png": "8139190",
        "37.png": "2166687",
        "10.png": "668296",
        "46.png": "0",
        "11.png": "216159",
        "08.png": "378355",
        "35.png": "0",
        "24.png": "425002",
        "12.png": "3211433",
        "40.png": "49261",
        "06.png": "89677",
        "47.png": "89506",
        "01.png": "213209",
        "56.png": "578594",
        "04.png": "0",
        "43.png": "0",
        "34.png": "0",
        "02.png": "533892",
        "27.png": "124921",
        "53.png": "1493",
        "42.png": "15043",
        "09.png": "587115",
        "07.png": "59539",
        "19.png": "1556273",
        "48.png": "194418",
        "38.png": "0",
        "49.png": "115022",
        "13.png": "2297586",
        "29.png": "22630",
        "28.png": "110124",
        "23.png": "3492507",
        "36.png": "412917",
        "57.png": "1447198",
        "22.png": "670741",
        "55.png": "0",
        "17.png": "1089285",
        "20.png": "642156",
        "59.png": "300470",
        "15.png": "212998",
        "54.png": "0",
        "21.png": "811590",
        "39.png": "0",
        "30.png": "152905",
        "45.png": "0",
        "31.png": "677676",
        "03.png": "276518",
        "58.png": "2080701",
        "18.png": "807419",
        "50.png": "70243",
        "52.png": "436610",
        "44.png": "36285",
        "32.png": "1362950",
        "14.png": "67739"
    },
    "Mag": {
        "41.png": "0",
        "25.png": "0",
        "26.png": "0",
        "16.png": "0",
        "33.png": "0",
        "51.png": "0",
        "05.png": "0",
        "37.png": "0",
        "10.png": "0",
        "46.png": "0",
        "11.png": "0",
        "08.png": "0",
        "35.png": "0",
        "24.png": "0",
        "12.png": "0",
        "40.png": "0",
        "06.png": "0",
        "47.png": "0",
        "01.png": "0",
        "56.png": "0",
        "04.png": "0",
        "43.png": "0",
        "34.png": "0",
        "02.png": "0",
        "27.png": "0",
        "53.png": "0",
        "42.png": "0",
        "09.png": "0",
        "07.png": "0",
        "19.png": "0",
        "48.png": "0",
        "38.png": "0",
        "49.png": "0",
        "13.png": "0",
        "29.png": "0",
        "28.png": "0",
        "23.png": "0",
        "36.png": "0",
        "57.png": "0",
        "22.png": "0",
        "55.png": "0",
        "17.png": "0",
        "20.png": "0",
        "59.png": "0",
        "15.png": "0",
        "54.png": "0",
        "21.png": "0",
        "39.png": "0",
        "30.png": "0",
        "45.png": "0",
        "31.png": "0",
        "03.png": "0",
        "58.png": "0",
        "18.png": "0",
        "50.png": "0",
        "52.png": "0",
        "44.png": "0",
        "32.png": "0",
        "14.png": "0"
    },
    "Brt": {
        "41.png": "0",
        "25.png": "0",
        "26.png": "0",
        "16.png": "0",
        "33.png": "0",
        "51.png": "190707",
        "05.png": "0",
        "37.png": "0",
        "10.png": "0",
        "46.png": "0",
        "11.png": "0",
        "08.png": "0",
        "35.png": "8",
        "24.png": "0",
        "12.png": "0",
        "40.png": "0",
        "06.png": "0",
        "47.png": "0",
        "01.png": "0",
        "56.png": "1982796",
        "04.png": "0",
        "43.png": "0",
        "34.png": "0",
        "02.png": "0",
        "27.png": "0",
        "53.png": "822829",
        "42.png": "0",
        "09.png": "0",
        "07.png": "160053",
        "19.png": "0",
        "48.png": "1056315",
        "38.png": "0",
        "49.png": "284790",
        "13.png": "0",
        "29.png": "0",
        "28.png": "0",
        "23.png": "0",
        "36.png": "0",
        "57.png": "5173726",
        "22.png": "108",
        "55.png": "714280",
        "17.png": "0",
        "20.png": "0",
        "59.png": "4214352",
        "15.png": "14325",
        "54.png": "563514",
        "21.png": "0",
        "39.png": "0",
        "30.png": "0",
        "45.png": "0",
        "31.png": "0",
        "03.png": "0",
        "58.png": "5118867",
        "18.png": "0",
        "50.png": "899719",
        "52.png": "1728272",
        "44.png": "0",
        "32.png": "0",
        "14.png": "0"
    },
    "Po": {
        "41.png": "0",
        "25.png": "0",
        "26.png": "0",
        "16.png": "0",
        "33.png": "0",
        "51.png": "0",
        "05.png": "0",
        "37.png": "0",
        "10.png": "0",
        "46.png": "0",
        "11.png": "0",
        "08.png": "0",
        "35.png": "0",
        "24.png": "0",
        "12.png": "0",
        "40.png": "0",
        "06.png": "0",
        "47.png": "0",
        "01.png": "0",
        "56.png": "0",
        "04.png": "0",
        "43.png": "0",
        "34.png": "0",
        "02.png": "0",
        "27.png": "0",
        "53.png": "0",
        "42.png": "0",
        "09.png": "0",
        "07.png": "0",
        "19.png": "0",
        "48.png": "0",
        "38.png": "0",
        "49.png": "0",
        "13.png": "0",
        "29.png": "0",
        "28.png": "0",
        "23.png": "0",
        "36.png": "0",
        "57.png": "0",
        "22.png": "0",
        "55.png": "0",
        "17.png": "0",
        "20.png": "0",
        "59.png": "0",
        "15.png": "0",
        "54.png": "0",
        "21.png": "0",
        "39.png": "0",
        "30.png": "0",
        "45.png": "0",
        "31.png": "0",
        "03.png": "0",
        "58.png": "0",
        "18.png": "0",
        "50.png": "0",
        "52.png": "0",
        "44.png": "0",
        "32.png": "0",
        "14.png": "0"
    },
    "PyMrc": {
        "41.png": "1365183",
        "25.png": "486122",
        "26.png": "4434561",
        "16.png": "3221426",
        "33.png": "3872252",
        "51.png": "3251272",
        "05.png": "0",
        "37.png": "0",
        "10.png": "5361105",
        "46.png": "106940",
        "11.png": "5269836",
        "08.png": "2867003",
        "35.png": "7857555",
        "24.png": "3526056",
        "12.png": "3177462",
        "40.png": "2011069",
        "06.png": "3550839",
        "47.png": "0",
        "01.png": "5042649",
        "56.png": "3571106",
        "04.png": "0",
        "43.png": "2979412",
        "34.png": "273406",
        "02.png": "0",
        "27.png": "2626304",
        "53.png": "1301547",
        "42.png": "85706",
        "09.png": "3961784",
        "07.png": "2601187",
        "19.png": "1435461",
        "48.png": "3076038",
        "38.png": "0",
        "49.png": "3574216",
        "13.png": "3845182",
        "29.png": "4426724",
        "28.png": "1812091",
        "23.png": "1466301",
        "36.png": "1055967",
        "57.png": "104397",
        "22.png": "1868581",
        "55.png": "1687822",
        "17.png": "298554",
        "20.png": "333109",
        "59.png": "200650",
        "15.png": "4831745",
        "54.png": "3148664",
        "21.png": "2965999",
        "39.png": "0",
        "30.png": "3432198",
        "45.png": "293604",
        "31.png": "1117368",
        "03.png": "0",
        "58.png": "0",
        "18.png": "736451",
        "50.png": "1413529",
        "52.png": "381704",
        "44.png": "1019784",
        "32.png": "620601",
        "14.png": "2870682"
    },
    "Pn": {
        "41.png": "0",
        "25.png": "0",
        "26.png": "0",
        "16.png": "0",
        "33.png": "0",
        "51.png": "0",
        "05.png": "0",
        "37.png": "0",
        "10.png": "0",
        "46.png": "0",
        "11.png": "0",
        "08.png": "0",
        "35.png": "0",
        "24.png": "0",
        "12.png": "0",
        "40.png": "0",
        "06.png": "0",
        "47.png": "0",
        "01.png": "0",
        "56.png": "0",
        "04.png": "0",
        "43.png": "0",
        "34.png": "0",
        "02.png": "0",
        "27.png": "0",
        "53.png": "0",
        "42.png": "0",
        "09.png": "0",
        "07.png": "0",
        "19.png": "0",
        "48.png": "0",
        "38.png": "0",
        "49.png": "0",
        "13.png": "0",
        "29.png": "0",
        "28.png": "0",
        "23.png": "0",
        "36.png": "0",
        "57.png": "0",
        "22.png": "0",
        "55.png": "0",
        "17.png": "0",
        "20.png": "0",
        "59.png": "0",
        "15.png": "0",
        "54.png": "0",
        "21.png": "0",
        "39.png": "0",
        "30.png": "0",
        "45.png": "0",
        "31.png": "0",
        "03.png": "0",
        "58.png": "0",
        "18.png": "0",
        "50.png": "0",
        "52.png": "0",
        "44.png": "0",
        "32.png": "0",
        "14.png": "0"
    },
    "Sph": {
        "41.png": "1313379",
        "25.png": "5881961",
        "26.png": "943926",
        "16.png": "212460",
        "33.png": "2213452",
        "51.png": "344617",
        "05.png": "0",
        "37.png": "5512128",
        "10.png": "2173451",
        "46.png": "2415864",
        "11.png": "1864663",
        "08.png": "1867442",
        "35.png": "0",
        "24.png": "1182907",
        "12.png": "1662808",
        "40.png": "2264897",
        "06.png": "1361270",
        "47.png": "3437923",
        "01.png": "1198438",
        "56.png": "0",
        "04.png": "7657030",
        "43.png": "2040011",
        "34.png": "8133699",
        "02.png": "6443784",
        "27.png": "1393474",
        "53.png": "0",
        "42.png": "7199545",
        "09.png": "3694838",
        "07.png": "1259119",
        "19.png": "2793220",
        "48.png": "221865",
        "38.png": "8535866",
        "49.png": "909619",
        "13.png": "1632230",
        "29.png": "1827515",
        "28.png": "578934",
        "23.png": "2313704",
        "36.png": "2215450",
        "57.png": "0",
        "22.png": "1385074",
        "55.png": "0",
        "17.png": "2616122",
        "20.png": "3402872",
        "59.png": "840705",
        "15.png": "208626",
        "54.png": "39058",
        "21.png": "1820201",
        "39.png": "8585523",
        "30.png": "305011",
        "45.png": "2109227",
        "31.png": "3085835",
        "03.png": "7551853",
        "58.png": "182859",
        "18.png": "2098036",
        "50.png": "397776",
        "52.png": "145467",
        "44.png": "4317293",
        "32.png": "3704751",
        "14.png": "160802"
    },
    "Apy": {
        "41.png": "0",
        "25.png": "0",
        "26.png": "0",
        "16.png": "0",
        "33.png": "0",
        "51.png": "0",
        "05.png": "0",
        "37.png": "0",
        "10.png": "0",
        "46.png": "0",
        "11.png": "0",
        "08.png": "0",
        "35.png": "0",
        "24.png": "0",
        "12.png": "0",
        "40.png": "0",
        "06.png": "0",
        "47.png": "0",
        "01.png": "0",
        "56.png": "0",
        "04.png": "0",
        "43.png": "0",
        "34.png": "0",
        "02.png": "0",
        "27.png": "0",
        "53.png": "0",
        "42.png": "0",
        "09.png": "0",
        "07.png": "0",
        "19.png": "0",
        "48.png": "0",
        "38.png": "0",
        "49.png": "0",
        "13.png": "0",
        "29.png": "0",
        "28.png": "0",
        "23.png": "0",
        "36.png": "0",
        "57.png": "0",
        "22.png": "0",
        "55.png": "0",
        "17.png": "0",
        "20.png": "0",
        "59.png": "0",
        "15.png": "0",
        "54.png": "0",
        "21.png": "0",
        "39.png": "0",
        "30.png": "0",
        "45.png": "0",
        "31.png": "0",
        "03.png": "0",
        "58.png": "0",
        "18.png": "0",
        "50.png": "0",
        "52.png": "0",
        "44.png": "0",
        "32.png": "0",
        "14.png": "0"
    },
    "Hem": {
        "41.png": "0",
        "25.png": "0",
        "26.png": "0",
        "16.png": "0",
        "33.png": "0",
        "51.png": "0",
        "05.png": "0",
        "37.png": "0",
        "10.png": "0",
        "46.png": "0",
        "11.png": "0",
        "08.png": "0",
        "35.png": "0",
        "24.png": "0",
        "12.png": "0",
        "40.png": "0",
        "06.png": "0",
        "47.png": "0",
        "01.png": "0",
        "56.png": "0",
        "04.png": "0",
        "43.png": "0",
        "34.png": "0",
        "02.png": "0",
        "27.png": "0",
        "53.png": "0",
        "42.png": "0",
        "09.png": "0",
        "07.png": "0",
        "19.png": "0",
        "48.png": "0",
        "38.png": "0",
        "49.png": "0",
        "13.png": "0",
        "29.png": "0",
        "28.png": "0",
        "23.png": "0",
        "36.png": "0",
        "57.png": "0",
        "22.png": "0",
        "55.png": "0",
        "17.png": "0",
        "20.png": "0",
        "59.png": "0",
        "15.png": "0",
        "54.png": "0",
        "21.png": "0",
        "39.png": "0",
        "30.png": "0",
        "45.png": "0",
        "31.png": "0",
        "03.png": "0",
        "58.png": "0",
        "18.png": "0",
        "50.png": "0",
        "52.png": "0",
        "44.png": "0",
        "32.png": "0",
        "14.png": "0"
    },
    "TntTtr": {
        "41.png": "1555054",
        "25.png": "0",
        "26.png": "0",
        "16.png": "0",
        "33.png": "0",
        "51.png": "0",
        "05.png": "0",
        "37.png": "0",
        "10.png": "0",
        "46.png": "2131870",
        "11.png": "0",
        "08.png": "0",
        "35.png": "0",
        "24.png": "0",
        "12.png": "0",
        "40.png": "943976",
        "06.png": "239429",
        "47.png": "721628",
        "01.png": "179304",
        "56.png": "0",
        "04.png": "0",
        "43.png": "1712483",
        "34.png": "0",
        "02.png": "0",
        "27.png": "0",
        "53.png": "120861",
        "42.png": "713877",
        "09.png": "0",
        "07.png": "0",
        "19.png": "2761",
        "48.png": "0",
        "38.png": "0",
        "49.png": "0",
        "13.png": "0",
        "29.png": "0",
        "28.png": "0",
        "23.png": "0",
        "36.png": "1024813",
        "57.png": "0",
        "22.png": "4",
        "55.png": "361615",
        "17.png": "0",
        "20.png": "27252",
        "59.png": "0",
        "15.png": "0",
        "54.png": "450451",
        "21.png": "0",
        "39.png": "0",
        "30.png": "273550",
        "45.png": "4922472",
        "31.png": "580303",
        "03.png": "0",
        "58.png": "0",
        "18.png": "0",
        "50.png": "0",
        "52.png": "0",
        "44.png": "2491677",
        "32.png": "0",
        "14.png": "0"
    },
    "Kvl": {
        "41.png": "0",
        "25.png": "0",
        "26.png": "0",
        "16.png": "0",
        "33.png": "0",
        "51.png": "0",
        "05.png": "0",
        "37.png": "0",
        "10.png": "0",
        "46.png": "0",
        "11.png": "0",
        "08.png": "0",
        "35.png": "0",
        "24.png": "0",
        "12.png": "0",
        "40.png": "0",
        "06.png": "0",
        "47.png": "0",
        "01.png": "0",
        "56.png": "0",
        "04.png": "0",
        "43.png": "0",
        "34.png": "0",
        "02.png": "0",
        "27.png": "0",
        "53.png": "0",
        "42.png": "0",
        "09.png": "0",
        "07.png": "0",
        "19.png": "0",
        "48.png": "0",
        "38.png": "0",
        "49.png": "0",
        "13.png": "0",
        "29.png": "0",
        "28.png": "0",
        "23.png": "0",
        "36.png": "0",
        "57.png": "0",
        "22.png": "0",
        "55.png": "0",
        "17.png": "0",
        "20.png": "0",
        "59.png": "0",
        "15.png": "0",
        "54.png": "0",
        "21.png": "0",
        "39.png": "0",
        "30.png": "0",
        "45.png": "0",
        "31.png": "0",
        "03.png": "0",
        "58.png": "0",
        "18.png": "0",
        "50.png": "0",
        "52.png": "0",
        "44.png": "0",
        "32.png": "0",
        "14.png": "0"
    }
}